CHANGES.txt
README.txt
bootstrap.py
buildout.cfg
setup.py
hurry/__init__.py
hurry.jstree.egg-info/PKG-INFO
hurry.jstree.egg-info/SOURCES.txt
hurry.jstree.egg-info/dependency_links.txt
hurry.jstree.egg-info/entry_points.txt
hurry.jstree.egg-info/namespace_packages.txt
hurry.jstree.egg-info/not-zip-safe
hurry.jstree.egg-info/requires.txt
hurry.jstree.egg-info/top_level.txt
hurry/jstree/__init__.py
hurry/jstree/jstree.txt
hurry/jstree/tests.py
hurry/jstree/jstree-build/jquery.jstree.js
hurry/jstree/jstree-build/_lib/jquery.cookie.js
hurry/jstree/jstree-build/_lib/jquery.hotkeys.js
hurry/jstree/jstree-build/themes/apple/bg.jpg
hurry/jstree/jstree-build/themes/apple/d.png
hurry/jstree/jstree-build/themes/apple/dot_for_ie.gif
hurry/jstree/jstree-build/themes/apple/style.css
hurry/jstree/jstree-build/themes/apple/throbber.gif
hurry/jstree/jstree-build/themes/classic/d.png
hurry/jstree/jstree-build/themes/classic/dot_for_ie.gif
hurry/jstree/jstree-build/themes/classic/style.css
hurry/jstree/jstree-build/themes/classic/throbber.gif
hurry/jstree/jstree-build/themes/default/d.gif
hurry/jstree/jstree-build/themes/default/d.png
hurry/jstree/jstree-build/themes/default/style.css
hurry/jstree/jstree-build/themes/default/throbber.gif
hurry/jstree/jstree-build/themes/default-rtl/d.gif
hurry/jstree/jstree-build/themes/default-rtl/d.png
hurry/jstree/jstree-build/themes/default-rtl/dots.gif
hurry/jstree/jstree-build/themes/default-rtl/style.css
hurry/jstree/jstree-build/themes/default-rtl/throbber.gif