Metadata-Version: 1.0
Name: hurry.jstree
Version: 1.0rc2.1
Summary: hurry.resource resources for JsTree
Home-page: UNKNOWN
Author: Martijn Faassen /Izhar Firdaus
Author-email: faassen@startifact.com
License: MIT
Platform: UNKNOWN
Classifier: Programming Language :: Python
